daio/__init__.py
daio/h5.py
daio/video.py
daio-1.0.0.dist-info/licenses/LICENSE
daio-1.0.0.dist-info/METADATA
daio-1.0.0.dist-info/WHEEL
daio-1.0.0.dist-info/top_level.txt
daio-1.0.0.dist-info/RECORD
