Metadata-Version: 2.4
Name: daio
Version: 1.0.0
Summary: video and data IO tools for Python
Author: jlab.berlin
License: MIT
Project-URL: Homepage, https://github.com/danionella/daio
Keywords: python,HDF5,data IO,video IO
Requires-Python: >=3.8
License-File: LICENSE
Requires-Dist: numpy
Requires-Dist: av
Requires-Dist: h5py
Requires-Dist: hdf5plugin
Dynamic: license-file
